ez_setup.py
setup.py
setuptools-0.6c9-py2.5.egg
AMQPQueue.egg-info/PKG-INFO
AMQPQueue.egg-info/SOURCES.txt
AMQPQueue.egg-info/dependency_links.txt
AMQPQueue.egg-info/requires.txt
AMQPQueue.egg-info/top_level.txt
amqpqueue/__init__.py
amqpqueue/amqpqueue.py
amqpqueue/queuefactory.py
amqpqueue/worker.py
testamqpqueue/basic.py
testamqpqueue/flickr_uploader.py
testamqpqueue/inotify_logger.py
testamqpqueue/inotify_worker.py
testamqpqueue/solrUploader.py
testamqpqueue/testHTTPWorker.py
testamqpqueue/testWorker.py