Metadata-Version: 1.0
Name: AMQPQueue
Version: 0.4.2
Summary: AMQPQueue - Python Queue interface for AMQP
Home-page: UNKNOWN
Author: Ben O'Steen
Author-email: bosteen@gmail.com
License: UNKNOWN
Platform: UNKNOWN
